invenio_subjects_mesh/__init__.py
invenio_subjects_mesh/vocabularies/__init__.py
invenio_subjects_mesh/vocabularies/subjects_mesh.csv
invenio_subjects_mesh/vocabularies/vocabularies.yaml
invenio_subjects_mesh-2025.1.15.2.dist-info/licenses/LICENSE
invenio_subjects_mesh-2025.1.15.2.dist-info/METADATA
invenio_subjects_mesh-2025.1.15.2.dist-info/WHEEL
invenio_subjects_mesh-2025.1.15.2.dist-info/entry_points.txt
invenio_subjects_mesh-2025.1.15.2.dist-info/top_level.txt
invenio_subjects_mesh-2025.1.15.2.dist-info/RECORD
