Metadata-Version: 2.4
Name: invenio-subjects-mesh
Version: 2025.1.15.2
Summary: MeSH subject terms with qualifiers
Author-email: Northwestern University <DL_FSM_GDS@e.northwestern.edu>
License: MIT License
Project-URL: Repository, https://github.com/galterlibrary/invenio-subjects-mesh
Keywords: invenio,inveniordm,subjects,MeSH
Classifier: Environment :: Web Environment
Classifier: Intended Audience :: Developers
Classifier: License :: OSI Approved :: MIT License
Classifier: Operating System :: OS Independent
Classifier: Programming Language :: Python
Classifier: Topic :: Internet :: WWW/HTTP :: Dynamic Content
Classifier: Topic :: Software Development :: Libraries :: Python Modules
Classifier: Programming Language :: Python :: 3
Classifier: Programming Language :: Python :: 3.9
Classifier: Programming Language :: Python :: 3.11
Classifier: Programming Language :: Python :: 3.12
Classifier: Programming Language :: Python :: 3.13
Requires-Python: >=3.9
License-File: LICENSE
Requires-Dist: galter-subjects-utils<2.0,>=0.7.0
Provides-Extra: dev
Requires-Dist: check-manifest>=0.49; extra == "dev"
Requires-Dist: invenio-search[opensearch2]<3.0,>=2.1.0; extra == "dev"
Requires-Dist: invoke<3.0,>=2.2; extra == "dev"
Requires-Dist: pyyaml>=5.4.1; extra == "dev"
Requires-Dist: pytest-invenio<3.0.0,>=2.1.1; extra == "dev"
Provides-Extra: dev-pre
Requires-Dist: check-manifest>=0.49; extra == "dev-pre"
Requires-Dist: invenio-search[opensearch2]<4.0.0,>=3.0.0; extra == "dev-pre"
Requires-Dist: invoke<3.0,>=2.2; extra == "dev-pre"
Requires-Dist: pyyaml>=5.4.1; extra == "dev-pre"
Requires-Dist: pytest-invenio<4.0.0,>=3.3.0; extra == "dev-pre"
Dynamic: license-file
